sysid/__init__.py
sysid/_version.py
sysid/ss.py
sysid/subspace.py
sysid/subspace_stochastic.py
sysid/test_ss.py
sysid/test_subspace.py
sysid-0.2.0.dist-info/LICENSE
sysid-0.2.0.dist-info/METADATA
sysid-0.2.0.dist-info/WHEEL
sysid-0.2.0.dist-info/top_level.txt
sysid-0.2.0.dist-info/RECORD
