Metadata-Version: 2.1
Name: sysid
Version: 0.2.0
Summary: Python system id.
Home-page: https://github.com/jgoppert/sysid
Author: James Goppert
Author-email: james.goppert@gmail.com
Maintainer: James Goppert
Maintainer-email: james.goppert@gmail.com
License: BSD
Download-URL: https://github.com/jgoppert/sysid
Platform: Windows
Platform: Linux
Platform: Solaris
Platform: Mac OS-X
Platform: Unix
Classifier: Development Status :: 1 - Planning
Classifier: Intended Audience :: Science/Research
Classifier: Intended Audience :: Developers
Classifier: License :: OSI Approved :: GNU General Public License v3 or later (GPLv3+)
Classifier: Programming Language :: Python
Classifier: Programming Language :: Python :: 3
Classifier: Programming Language :: Other
Classifier: Topic :: Software Development
Classifier: Topic :: Scientific/Engineering :: Artificial Intelligence
Classifier: Topic :: Scientific/Engineering :: Mathematics
Classifier: Topic :: Scientific/Engineering :: Physics
Classifier: Operating System :: Microsoft :: Windows
Classifier: Operating System :: POSIX
Classifier: Operating System :: Unix
Classifier: Operating System :: MacOS
Requires-Dist: scipy
Requires-Dist: numpy
